xai_creditscorecard/__init__.py
xai_creditscorecard/scorecard_shap.cp313-win_amd64.pyd
xai_creditscorecard/scorecard_shap.py
xai_creditscorecard-1.1.4.dist-info/licenses/LICENSE
xai_creditscorecard-1.1.4.dist-info/METADATA
xai_creditscorecard-1.1.4.dist-info/WHEEL
xai_creditscorecard-1.1.4.dist-info/top_level.txt
xai_creditscorecard-1.1.4.dist-info/RECORD
