Metadata-Version: 2.4
Name: xai_creditscorecard
Version: 1.1.4
Summary: A scorecard library with SHAP integration
Author-email: Rivalani Hlongwane <rhlongwa@gmail.com>
License-Expression: MIT
Project-URL: Homepage, https://github.com/rhlongwa/xai_creditscorecard
Requires-Python: >=3.8
License-File: LICENSE
Requires-Dist: numpy<2.0.0,>=1.26.0
Requires-Dist: pandas<3.0.0,>=1.3.0
Requires-Dist: scikit-learn>=1.0.0
Requires-Dist: shap>=0.41.0
Requires-Dist: plotly>=5.0.0
Requires-Dist: xgboost>=1.5.0
Requires-Dist: catboost>=1.0.0
Dynamic: license-file
